qwen_agent/__init__.py
qwen_agent/agent.py
qwen_agent/log.py
qwen_agent/multi_agent_hub.py
qwen_agent/settings.py
qwen_agent/agents/__init__.py
qwen_agent/agents/article_agent.py
qwen_agent/agents/assistant.py
qwen_agent/agents/dialogue_retrieval_agent.py
qwen_agent/agents/dialogue_simulator.py
qwen_agent/agents/fncall_agent.py
qwen_agent/agents/group_chat.py
qwen_agent/agents/group_chat_auto_router.py
qwen_agent/agents/group_chat_creator.py
qwen_agent/agents/human_simulator.py
qwen_agent/agents/memo_assistant.py
qwen_agent/agents/react_chat.py
qwen_agent/agents/router.py
qwen_agent/agents/tir_agent.py
qwen_agent/agents/user_agent.py
qwen_agent/agents/virtual_memory_agent.py
qwen_agent/agents/write_from_scratch.py
qwen_agent/agents/doc_qa/__init__.py
qwen_agent/agents/doc_qa/basic_doc_qa.py
qwen_agent/agents/doc_qa/parallel_doc_qa.py
qwen_agent/agents/doc_qa/parallel_doc_qa_member.py
qwen_agent/agents/doc_qa/parallel_doc_qa_summary.py
qwen_agent/agents/keygen_strategies/__init__.py
qwen_agent/agents/keygen_strategies/gen_keyword.py
qwen_agent/agents/keygen_strategies/gen_keyword_with_knowledge.py
qwen_agent/agents/keygen_strategies/split_query.py
qwen_agent/agents/keygen_strategies/split_query_then_gen_keyword.py
qwen_agent/agents/keygen_strategies/split_query_then_gen_keyword_with_knowledge.py
qwen_agent/agents/writing/__init__.py
qwen_agent/agents/writing/continue_writing.py
qwen_agent/agents/writing/expand_writing.py
qwen_agent/agents/writing/outline_writing.py
qwen_agent/gui/__init__.py
qwen_agent/gui/gradio_dep.py
qwen_agent/gui/gradio_utils.py
qwen_agent/gui/utils.py
qwen_agent/gui/web_ui.py
qwen_agent/gui/assets/app.css
qwen_agent/gui/assets/appBot.css
qwen_agent/gui/assets/logo.jpeg
qwen_agent/gui/assets/user.jpeg
qwen_agent/llm/__init__.py
qwen_agent/llm/azure.py
qwen_agent/llm/base.py
qwen_agent/llm/function_calling.py
qwen_agent/llm/oai.py
qwen_agent/llm/openvino.py
qwen_agent/llm/qwen_dashscope.py
qwen_agent/llm/qwenaudio_dashscope.py
qwen_agent-0.0.30.dist-info/licenses/LICENSE
qwen_agent-0.0.30.dist-info/METADATA
qwen_agent-0.0.30.dist-info/WHEEL
qwen_agent-0.0.30.dist-info/top_level.txt
qwen_agent-0.0.30.dist-info/RECORD
