Metadata-Version: 2.4
Name: qwen-agent
Version: 0.0.30
Summary: Qwen-Agent: Enhancing LLMs with Agent Workflows, RAG, Function Calling, and Code Interpreter.
Home-page: https://github.com/QwenLM/Qwen-Agent
Author: Qwen Team
Author-email: tujianhong.tjh@alibaba-inc.com
Keywords: LLM,Agent,Function Calling,RAG,Code Interpreter
License-File: LICENSE
Requires-Dist: dashscope>=1.11.0
Requires-Dist: eval_type_backport
Requires-Dist: json5
Requires-Dist: jsonlines
Requires-Dist: jsonschema
Requires-Dist: openai
Requires-Dist: pydantic>=2.3.0
Requires-Dist: requests
Requires-Dist: tiktoken
Provides-Extra: rag
Requires-Dist: charset-normalizer; extra == "rag"
Requires-Dist: rank_bm25; extra == "rag"
Requires-Dist: jieba; extra == "rag"
Requires-Dist: snowballstemmer; extra == "rag"
Requires-Dist: beautifulsoup4; extra == "rag"
Requires-Dist: pdfminer.six; extra == "rag"
Requires-Dist: pdfplumber; extra == "rag"
Requires-Dist: python-docx; extra == "rag"
Requires-Dist: python-pptx; extra == "rag"
Requires-Dist: pandas; extra == "rag"
Requires-Dist: tabulate; extra == "rag"
Provides-Extra: mcp
Requires-Dist: mcp; extra == "mcp"
Provides-Extra: python-executor
Requires-Dist: pebble; extra == "python-executor"
Requires-Dist: multiprocess; extra == "python-executor"
Requires-Dist: timeout_decorator; extra == "python-executor"
Requires-Dist: python-dateutil; extra == "python-executor"
Requires-Dist: sympy; extra == "python-executor"
Requires-Dist: numpy; extra == "python-executor"
Requires-Dist: scipy; extra == "python-executor"
Provides-Extra: code-interpreter
Requires-Dist: anyio>=3.7.1; extra == "code-interpreter"
Requires-Dist: fastapi>=0.103.1; extra == "code-interpreter"
Requires-Dist: jupyter>=1.0.0; extra == "code-interpreter"
Requires-Dist: matplotlib; extra == "code-interpreter"
Requires-Dist: numpy; extra == "code-interpreter"
Requires-Dist: pandas; extra == "code-interpreter"
Requires-Dist: pillow; extra == "code-interpreter"
Requires-Dist: seaborn; extra == "code-interpreter"
Requires-Dist: sympy; extra == "code-interpreter"
Requires-Dist: uvicorn>=0.23.2; extra == "code-interpreter"
Provides-Extra: gui
Requires-Dist: pydantic==2.9.2; extra == "gui"
Requires-Dist: pydantic-core==2.23.4; extra == "gui"
Requires-Dist: gradio==5.23.1; extra == "gui"
Requires-Dist: gradio-client==1.8.0; extra == "gui"
Requires-Dist: modelscope_studio==1.1.7; extra == "gui"
Dynamic: author
Dynamic: author-email
Dynamic: description
Dynamic: description-content-type
Dynamic: home-page
Dynamic: keywords
Dynamic: license-file
Dynamic: provides-extra
Dynamic: requires-dist
Dynamic: summary
